pace_py_log_lib/__init__.py
pace_py_log_lib/logger.py
pace_python_logger-0.0.3.dist-info/LICENSE
pace_python_logger-0.0.3.dist-info/METADATA
pace_python_logger-0.0.3.dist-info/WHEEL
pace_python_logger-0.0.3.dist-info/top_level.txt
pace_python_logger-0.0.3.dist-info/RECORD
