Metadata-Version: 2.1
Name: pace_python_logger
Version: 0.0.3
Summary: Python logging library for Productivity Assessment of Copilots with Econometrics (PACE)
Author-email: Aadharsh Kannan <akannan@microsoft.com>
Project-URL: Homepage, https://github.com/microsoft/PACE/logging_library/python
Project-URL: Bug Tracker, https://github.com/microsoft/PACE/logging_library/python/issues
Classifier: Programming Language :: Python :: 3
Classifier: License :: OSI Approved :: MIT License
Classifier: Operating System :: OS Independent
Requires-Python: >=3.7
License-File: LICENSE
